sensorflex/__init__.py
sensorflex/core/runtime/__init__.py
sensorflex/core/runtime/_flow.py
sensorflex/core/runtime/_graph.py
sensorflex/core/runtime/_node.py
sensorflex/library/cv/__init__.py
sensorflex/library/cv/_aruco.py
sensorflex/library/cv/_filtering.py
sensorflex/library/cv/_realsense.py
sensorflex/library/cv/_webcam.py
sensorflex/library/io/__init__.py
sensorflex/library/net/__init__.py
sensorflex/library/net/_distributed.py
sensorflex/library/net/_webrtc.py
sensorflex/library/net/_websocket.py
sensorflex/library/rtc/__init__.py
sensorflex/library/rtc/_webrtc.py
sensorflex/library/vis/__init__.py
sensorflex/library/vis/_rerun.py
sensorflex/utils/logging.py
sensorflex-0.1.4.dist-info/METADATA
sensorflex-0.1.4.dist-info/WHEEL
sensorflex-0.1.4.dist-info/licenses/LICENSE
sensorflex-0.1.4.dist-info/RECORD
